ae_python_imbalance/__init__.py
python_imbalance/__init__.py
ae_python_imbalance-0.0.1.dist-info/METADATA
ae_python_imbalance-0.0.1.dist-info/WHEEL
ae_python_imbalance-0.0.1.dist-info/top_level.txt
ae_python_imbalance-0.0.1.dist-info/RECORD
